datavlt/__init__.py
datavlt/src/__init__.py
datavlt/src/config.py
datavlt/src/processor.py
datavlt/src/spec_methods.py
datavlt/src/storage.py
datavlt-0.2.1.dist-info/METADATA
datavlt-0.2.1.dist-info/WHEEL
datavlt-0.2.1.dist-info/top_level.txt
datavlt-0.2.1.dist-info/RECORD
