Metadata-Version: 2.4
Name: datavlt
Version: 0.2.1
Summary: A simple JSON-based data storage library with mfsapi integration
Author: maksalmaz
Classifier: Programming Language :: Python :: 3
Classifier: Operating System :: OS Independent
Requires-Python: >=3.10
Requires-Dist: mfsapi>=0.1.1
Dynamic: author
Dynamic: classifier
Dynamic: requires-dist
Dynamic: requires-python
Dynamic: summary
